pp/__init__.py
pp/app.py
pp/config.py
pp/constants.py
pp/data.py
pp/draw.py
pp/io.py
pp/log.py
pp/util.py
pp/viz.py
pandas_plotly-0.2.4.dist-info/LICENSE
pandas_plotly-0.2.4.dist-info/METADATA
pandas_plotly-0.2.4.dist-info/WHEEL
pandas_plotly-0.2.4.dist-info/top_level.txt
pandas_plotly-0.2.4.dist-info/RECORD
