Metadata-Version: 2.1
Name: pandas-plotly
Version: 0.2.4
License-File: LICENSE
Requires-Dist: numpy (>=1.21.2)
Requires-Dist: pandas (>=1.3.47)
Requires-Dist: plotly (>=5.1.0)
